crepe/__init__.py
crepe/__main__.py
crepe/cli.py
crepe/core.py
crepe-0.0.0.dist-info/DESCRIPTION.rst
crepe-0.0.0.dist-info/METADATA
crepe-0.0.0.dist-info/RECORD
crepe-0.0.0.dist-info/WHEEL
crepe-0.0.0.dist-info/entry_points.txt
crepe-0.0.0.dist-info/metadata.json
crepe-0.0.0.dist-info/top_level.txt
