Metadata-Version: 2.0
Name: crepe
Version: 0.0.0
Summary: CREPE pitch tracker
Home-page: https://github.com/marl/crepe
Author: Jong Wook Kim
Author-email: jongwook@nyu.edu
License: MIT
Keywords: tfrecord
Platform: UNKNOWN
Classifier: Development Status :: 3 - Alpha
Classifier: License :: OSI Approved :: MIT License
Classifier: Topic :: Multimedia :: Sound/Audio :: Analysis
Classifier: Programming Language :: Python :: 2
Classifier: Programming Language :: Python :: 2.7
Classifier: Programming Language :: Python :: 3
Classifier: Programming Language :: Python :: 3.5
Classifier: Programming Language :: Python :: 3.6
Requires-Dist: keras (==2.1.5)
Requires-Dist: numpy (>=1.14.0)
Requires-Dist: scipy (>=1.0.0)
Requires-Dist: matplotlib (>=2.1.0)
Requires-Dist: resampy (<0.3.0,>=0.2.0)
Requires-Dist: h5py (<3.0.0,>=2.7.0)
Requires-Dist: hmmlearn (<0.3.0,==0.2.0)
Requires-Dist: imageio (>=2.3.0)
Requires-Dist: scikit-learn (>=0.16)
